promptmigrate/__init__.py
promptmigrate/autorevision.py
promptmigrate/cli.py
promptmigrate/manager.py
promptmigrate-0.4.0.dist-info/licenses/LICENSE
promptmigrate-0.4.0.dist-info/METADATA
promptmigrate-0.4.0.dist-info/WHEEL
promptmigrate-0.4.0.dist-info/entry_points.txt
promptmigrate-0.4.0.dist-info/top_level.txt
promptmigrate-0.4.0.dist-info/RECORD
