Metadata-Version: 2.4
Name: promptmigrate
Version: 0.4.0
Summary: Schema‑like migration manager for LLM prompt collections
Author-email: PromptMigrate Team <opensource@example.com>
License: MIT
Project-URL: Homepage, https://github.com/promptmigrate/promptmigrate
Project-URL: Documentation, https://filippoleone.github.io/promptmigrate/
Project-URL: Issues, https://github.com/promptmigrate/promptmigrate/issues
Project-URL: Changelog, https://github.com/promptmigrate/promptmigrate/blob/main/CHANGELOG.md
Keywords: prompt‑engineering,llm,migration,revision,cli,prompt-management
Classifier: Development Status :: 4 - Beta
Classifier: Intended Audience :: Developers
Classifier: License :: OSI Approved :: MIT License
Classifier: Operating System :: OS Independent
Classifier: Programming Language :: Python :: 3
Classifier: Programming Language :: Python :: 3.9
Classifier: Programming Language :: Python :: 3.10
Classifier: Programming Language :: Python :: 3.11
Classifier: Programming Language :: Python :: 3.12
Classifier: Topic :: Software Development :: Libraries :: Python Modules
Classifier: Topic :: Scientific/Engineering :: Artificial Intelligence
Requires-Python: >=3.9
License-File: LICENSE
Requires-Dist: click>=8.1
Requires-Dist: pyyaml>=6.0
Provides-Extra: test
Requires-Dist: pytest>=8; extra == "test"
Requires-Dist: coverage[toml]>=7; extra == "test"
Requires-Dist: pytest-cov>=4.1; extra == "test"
Provides-Extra: dev
Requires-Dist: black>=23.0; extra == "dev"
Requires-Dist: isort>=5.12; extra == "dev"
Requires-Dist: flake8>=6.0; extra == "dev"
Requires-Dist: build>=0.10; extra == "dev"
Requires-Dist: twine>=4.0; extra == "dev"
Provides-Extra: docs
Requires-Dist: mkdocs>=1.5; extra == "docs"
Requires-Dist: mkdocs-material>=9.5; extra == "docs"
Requires-Dist: mkdocs-autorefs<1.0.0; extra == "docs"
Requires-Dist: mkdocstrings[python]<0.25,>=0.24; extra == "docs"
Dynamic: license-file
